setup.py
MPlearn_distributions/Binomialdistribution.py
MPlearn_distributions/Gaussiandistribution.py
MPlearn_distributions/Generaldistribution.py
MPlearn_distributions/__init__.py
MPlearn_distributions.egg-info/PKG-INFO
MPlearn_distributions.egg-info/SOURCES.txt
MPlearn_distributions.egg-info/dependency_links.txt
MPlearn_distributions.egg-info/not-zip-safe
MPlearn_distributions.egg-info/top_level.txt